<?xml version="1.0" encoding="utf-8"?>
<extension type="plugin" version="2.5" method="upgrade" group="hikashop">
    <name>eMundus - Hikashop</name>
    <creationDate>20 November 2019</creationDate>
    <version>4.0.1</version>
    <author>James Dean</author>
    <authorEmail>james@emundus.fr</authorEmail>
    <authorUrl>https://www.emundus.fr</authorUrl>
    <copyright>(C) 2010-${year} eMundus SAS. All rights reserved.</copyright>
    <license>GNU General Public License version 2 or later; see LICENSE.txt</license>
    <description>This plugin will insert and update orders in jos_emundus_hikashop</description>
    <files>
        <filename plugin="emundus_hikashop">emundus_hikashop.php</filename>
        <folder>form</folder>
        <folder>language</folder>
    </files>
    <config>
        <fields name="params" addfieldpath="/components/com_hikashop/fields">
            <fieldset name="basic">
            </fieldset>
        </fields>
    </config>
</extension>