<?xml version="1.0"?>
<contenttype>
  <name>Admission - Details</name>
  <fabrikversion>3.4.3</fabrikversion>
  <group join_id="" is_join="0" id="230" name="Admission - Details" label="Admission - Details" css="" published="1" created="2015-01-26 15:21:08" private="0">
    <params split_page="0" access="1" intro="" outro="" repeat_group_button="0" repeat_template="repeatgroup" repeat_max="" repeat_min="" repeat_add_access="1" repeat_delete_access="1" repeat_delete_access_user="" repeat_copy_element_values="0" group_columns="1" group_column_widths="" repeat_group_show_first="1" random="0"/>
    <element label="id" published="1" name="id" id="2412" plugin="internalid" created="2015-01-26 15:21:08" width="30" height="6" default="" hidden="1" eval="0" ordering="1" show_in_list_summary="0" filter_type="" filter_exact_match="0" link_to_detail="0" primary_key="0" auto_increment="0" access="1" use_in_page_title="0" parent_id="0">
      <params rollover="" hover_text_title="" comment="" password="0" maxlength="255" text_format="text" integer_length="6" decimal_length="2" text_format_string="" guess_linktype="0" disable="0" readonly="0" ck_value="" ck_default_label="" element_before_label="1" options_per_row="4" allow_frontend_addtocheckbox="0" chk-allowadd-onlylabel="0" chk-savenewadditions="0" radio_element_before_label="0" allow_frontend_addtoradio="0" rad-allowadd-onlylabel="0" rad-savenewadditions="0" use_wysiwyg="0" textarea-showmax="0" textarea-maxlength="255" multiple="0" allow_frontend_addtodropdown="0" dd-allowadd-onlylabel="0" dd-savenewadditions="0" drd_initial_selection="" ul_max_file_size="8000" ul_file_types="" ul_directory="" ul_email_file="0" ul_file_increment="0" upload_allow_folderselect="1" fu_fancy_upload="0" upload_delete_image="1" default_image="" make_link="0" fu_show_image_in_table="0" fu_show_image="0" image_library="gd2" fu_main_max_width="" fu_main_max_height="" make_thumbnail="0" thumb_dir="" thumb_prefix="" thumb_max_height="" thumb_max_width="" imagepath="/" selectImage_root_folder="/" image_front_end_select="0" show_image_in_table="0" image_float="none" link_url="" my_table_data="id" update_on_edit="0" date_table_format="Y-m-d" date_form_format="%Y-%m-%d" date_showtime="0" date_defaulttotoday="0" database_join_display_type="dropdown" joinType="simple" join_conn_id="-1" join_db_name="" join_key_column="" join_val_column="" database_join_where_sql="" diysql="" database_join_noselectionvalue="" fabrikdatabasejoin_frontend_add="0" link_target="_self" view_access="1" show_in_rss_feed="0" show_label_in_rss_feed="0" use_as_fake_key="0" element_alt_table_heading="" icon_folder="-1" custom_link="" use_as_row_class="0" filter_access="1" full_words_only="0" inc_in_adv_search="1" sum_on="0" sum_access="1" sum_split="" avg_on="0" avg_access="1" avg_split="" median_on="0" median_access="1" median_split="" count_on="0" count_condition="" count_access="1" count_split="" can_order="0" sub_options="{}" parent_linked="1"/>
    </element>
    <element label="time date" published="1" name="time_date" id="2413" plugin="date" created="2015-01-26 15:21:08" width="30" height="6" default="" hidden="1" eval="0" ordering="2" show_in_list_summary="1" filter_type="" filter_exact_match="0" link_to_detail="0" primary_key="0" auto_increment="0" access="1" use_in_page_title="0" parent_id="0">
      <params rollover="" hover_text_title="" comment="" password="0" maxlength="255" text_format="text" integer_length="6" decimal_length="2" text_format_string="" guess_linktype="0" disable="0" readonly="0" ck_value="" ck_default_label="" element_before_label="1" options_per_row="4" allow_frontend_addtocheckbox="0" chk-allowadd-onlylabel="0" chk-savenewadditions="0" radio_element_before_label="0" allow_frontend_addtoradio="0" rad-allowadd-onlylabel="0" rad-savenewadditions="0" use_wysiwyg="0" textarea-showmax="0" textarea-maxlength="255" multiple="0" allow_frontend_addtodropdown="0" dd-allowadd-onlylabel="0" dd-savenewadditions="0" drd_initial_selection="" ul_max_file_size="8000" ul_file_types="" ul_directory="" ul_email_file="0" ul_file_increment="0" upload_allow_folderselect="1" fu_fancy_upload="0" upload_delete_image="1" default_image="" make_link="0" fu_show_image_in_table="0" fu_show_image="0" image_library="gd2" fu_main_max_width="" fu_main_max_height="" make_thumbnail="0" thumb_dir="" thumb_prefix="" thumb_max_height="" thumb_max_width="" imagepath="/" selectImage_root_folder="/" image_front_end_select="0" show_image_in_table="0" image_float="none" link_url="" my_table_data="id" update_on_edit="0" date_table_format="%Y-%m-%d %H:%I:%S" date_form_format="%Y-%m-%d %H:%I:%S" date_showtime="0" date_time_format="%H:%M" date_defaulttotoday="1" date_firstday="0" database_join_display_type="dropdown" joinType="simple" join_conn_id="-1" join_db_name="" join_key_column="" join_val_column="" database_join_where_sql="" diysql="" database_join_noselectionvalue="" fabrikdatabasejoin_frontend_add="0" yoffset="" link_target="_self" view_access="1" show_in_rss_feed="0" show_label_in_rss_feed="0" use_as_fake_key="0" element_alt_table_heading="" icon_folder="-1" custom_link="" use_as_row_class="0" filter_access="1" full_words_only="0" inc_in_adv_search="1" sum_on="0" sum_access="1" sum_split="" avg_on="0" avg_access="1" avg_split="" median_on="0" median_access="1" median_split="" count_on="0" count_condition="" count_access="1" count_split="" can_order="0" sub_options="{}" parent_linked="1" date_store_as_local="0" date_alwaystoday="0" date_allow_typing_in_field="1" date_csv_offset_tz="0" date_advanced="0" date_allow_func="" use_as_rss_enclosure="0" tipseval="0" tipsoverelement="0" tiplocation="top" labelindetails="1" labelinlist="0" view_access_user="" list_view_access="1" encrypt="0" alt_list_heading="" custom_link_indetails="1" include_in_list_query="1" always_render="0" icon_hovertext="1" icon_file="" filter_length="20" filter_required="0" filter_build_method="0" filter_groupby="text" tablecss_header_class="" tablecss_header="" tablecss_cell_class="" tablecss_cell="" sum_label="Sum" avg_label="Average" avg_round="0" median_label="Median" count_label="Count" custom_calc_on="0" custom_calc_label="Custom" custom_calc_query="" custom_calc_access="8" custom_calc_split="" custom_calc_php="" validations="[]"/>
    </element>
    <element label="user" published="1" name="user" id="2414" plugin="user" created="2015-01-26 15:21:08" width="30" height="6" default="" hidden="1" eval="0" ordering="3" show_in_list_summary="1" filter_type="" filter_exact_match="0" link_to_detail="0" primary_key="0" auto_increment="0" access="1" use_in_page_title="0" parent_id="0">
      <params rollover="" hover_text_title="" comment="" password="0" maxlength="255" text_format="text" integer_length="6" decimal_length="2" text_format_string="" guess_linktype="0" disable="0" readonly="0" ck_value="" ck_default_label="" element_before_label="1" options_per_row="4" allow_frontend_addtocheckbox="0" chk-allowadd-onlylabel="0" chk-savenewadditions="0" radio_element_before_label="0" allow_frontend_addtoradio="0" rad-allowadd-onlylabel="0" rad-savenewadditions="0" use_wysiwyg="0" textarea-showmax="0" textarea-maxlength="255" multiple="0" allow_frontend_addtodropdown="0" dd-allowadd-onlylabel="0" dd-savenewadditions="0" drd_initial_selection="" ul_max_file_size="8000" ul_file_types="" ul_directory="" ul_email_file="0" ul_file_increment="0" upload_allow_folderselect="1" fu_fancy_upload="0" upload_delete_image="1" default_image="" make_link="0" fu_show_image_in_table="0" fu_show_image="0" image_library="gd2" fu_main_max_width="" fu_main_max_height="" make_thumbnail="0" thumb_dir="" thumb_prefix="" thumb_max_height="" thumb_max_width="" imagepath="/" selectImage_root_folder="/" image_front_end_select="0" show_image_in_table="0" image_float="none" link_url="" my_table_data="id" update_on_edit="1" date_table_format="Y-m-d" date_form_format="%Y-%m-%d" date_showtime="0" date_defaulttotoday="0" database_join_display_type="dropdown" joinType="simple" join_conn_id="-1" join_db_name="" join_key_column="" join_val_column="" database_join_where_sql="" diysql="" database_join_noselectionvalue="" fabrikdatabasejoin_frontend_add="0" link_target="_self" view_access="1" show_in_rss_feed="0" show_label_in_rss_feed="0" use_as_fake_key="0" element_alt_table_heading="" icon_folder="-1" custom_link="" use_as_row_class="0" filter_access="1" full_words_only="0" inc_in_adv_search="1" sum_on="0" sum_access="1" sum_split="" avg_on="0" avg_access="1" avg_split="" median_on="0" median_access="1" median_split="" count_on="0" count_condition="" count_access="1" count_split="" can_order="0" sub_options="{}" parent_linked="1"/>
      <join table_join="#__users" table_join_alias="" list_id="0" element_id="2414" join_from_table="" table_key="user" table_join_key="id" join_type="left" group_id="230">
        <params join-label="id" pk="`#__users`.`id`"/>
      </join>
    </element>
    <element label="student id" published="1" name="student_id" id="2415" plugin="field" created="2015-01-26 15:21:08" width="30" height="6" default="" hidden="1" eval="0" ordering="4" show_in_list_summary="1" filter_type="" filter_exact_match="0" link_to_detail="0" primary_key="0" auto_increment="0" access="1" use_in_page_title="0" parent_id="0">
      <params rollover="" hover_text_title="" comment="" password="0" maxlength="255" text_format="integer" integer_length="6" decimal_length="2" text_format_string="" guess_linktype="0" disable="0" readonly="0" ck_value="" ck_default_label="" element_before_label="1" options_per_row="4" allow_frontend_addtocheckbox="0" chk-allowadd-onlylabel="0" chk-savenewadditions="0" radio_element_before_label="0" allow_frontend_addtoradio="0" rad-allowadd-onlylabel="0" rad-savenewadditions="0" use_wysiwyg="0" textarea-showmax="0" textarea-maxlength="255" multiple="0" allow_frontend_addtodropdown="0" dd-allowadd-onlylabel="0" dd-savenewadditions="0" drd_initial_selection="" ul_max_file_size="8000" ul_file_types="" ul_directory="" ul_email_file="0" ul_file_increment="0" upload_allow_folderselect="1" fu_fancy_upload="0" upload_delete_image="1" default_image="" make_link="0" fu_show_image_in_table="0" fu_show_image="0" image_library="gd2" fu_main_max_width="" fu_main_max_height="" make_thumbnail="0" thumb_dir="" thumb_prefix="" thumb_max_height="" thumb_max_width="" imagepath="/" selectImage_root_folder="/" image_front_end_select="0" show_image_in_table="0" image_float="none" link_url="" my_table_data="id" update_on_edit="0" date_table_format="Y-m-d" date_form_format="%Y-%m-%d" date_showtime="0" date_defaulttotoday="0" database_join_display_type="dropdown" joinType="simple" join_conn_id="-1" join_db_name="" join_key_column="" join_val_column="" database_join_where_sql="" diysql="" database_join_noselectionvalue="" fabrikdatabasejoin_frontend_add="0" link_target="_self" view_access="1" show_in_rss_feed="0" show_label_in_rss_feed="0" use_as_fake_key="0" element_alt_table_heading="" icon_folder="-1" custom_link="" use_as_row_class="0" filter_access="1" full_words_only="0" inc_in_adv_search="1" sum_on="0" sum_access="1" sum_split="" avg_on="0" avg_access="1" avg_split="" median_on="0" median_access="1" median_split="" count_on="0" count_condition="" count_access="1" count_split="" can_order="0" sub_options="{}" parent_linked="1"/>
    </element>
    <element label="Final grade" published="1" name="final_grade" id="2416" plugin="dropdown" created="2015-01-26 15:21:08" width="30" height="6" default="" hidden="0" eval="0" ordering="5" show_in_list_summary="1" filter_type="" filter_exact_match="0" link_to_detail="0" primary_key="0" auto_increment="0" access="1" use_in_page_title="0" parent_id="0">
      <params sub_options="{&quot;sub_values&quot;:[&quot;0&quot;,&quot;4&quot;,&quot;3&quot;,&quot;2&quot;],&quot;sub_labels&quot;:[&quot;-- Please select --&quot;,&quot;Accepted&quot;,&quot;Waiting List&quot;,&quot;Rejected&quot;]}" multiple="0" dropdown_multisize="3" allow_frontend_addtodropdown="0" dd-allowadd-onlylabel="0" dd-savenewadditions="0" options_split_str="" dropdown_populate="" show_in_rss_feed="0" show_label_in_rss_feed="0" use_as_fake_key="0" use_as_rss_enclosure="0" rollover="" tipseval="0" tipsoverelement="0" tiplocation="top" labelindetails="1" labelinlist="0" comment="" view_access="1" list_view_access="1" encrypt="0" can_order="0" alt_list_heading="" custom_link="" custom_link_indetails="1" use_as_row_class="0" include_in_list_query="1" always_render="0" icon_folder="0" icon_hovertext="1" icon_file="" filter_length="20" filter_access="1" full_words_only="0" filter_required="0" filter_build_method="0" filter_groupby="text" inc_in_adv_search="1" tablecss_header_class="" tablecss_header="" tablecss_cell_class="" tablecss_cell="" sum_on="0" sum_label="Sum" sum_access="1" sum_split="" avg_on="0" avg_label="Average" avg_access="1" avg_round="0" avg_split="" median_on="0" median_label="Median" median_access="1" median_split="" count_on="0" count_label="Count" count_condition="" count_access="1" count_split="" custom_calc_on="0" custom_calc_label="Custom" custom_calc_query="" custom_calc_access="1" custom_calc_split="" custom_calc_php="" validations="[]" parent_linked="1" view_access_user=""/>
    </element>
    <element label="type grade" published="0" name="type_grade" id="2418" plugin="field" created="2015-01-26 15:21:08" width="30" height="6" default="candidature" hidden="1" eval="0" ordering="6" show_in_list_summary="1" filter_type="" filter_exact_match="0" link_to_detail="0" primary_key="0" auto_increment="0" access="1" use_in_page_title="0" parent_id="0">
      <params rollover="" hover_text_title="" comment="" password="0" maxlength="255" text_format="text" integer_length="6" decimal_length="2" text_format_string="" guess_linktype="0" disable="0" readonly="0" ck_value="" ck_default_label="" element_before_label="1" options_per_row="4" allow_frontend_addtocheckbox="0" chk-allowadd-onlylabel="0" chk-savenewadditions="0" radio_element_before_label="0" allow_frontend_addtoradio="0" rad-allowadd-onlylabel="0" rad-savenewadditions="0" use_wysiwyg="0" textarea-showmax="0" textarea-maxlength="255" multiple="0" allow_frontend_addtodropdown="0" dd-allowadd-onlylabel="0" dd-savenewadditions="0" drd_initial_selection="" ul_max_file_size="8000" ul_file_types="" ul_directory="" ul_email_file="0" ul_file_increment="0" upload_allow_folderselect="1" fu_fancy_upload="0" upload_delete_image="1" default_image="" make_link="0" fu_show_image_in_table="0" fu_show_image="0" image_library="gd2" fu_main_max_width="" fu_main_max_height="" make_thumbnail="0" thumb_dir="" thumb_prefix="" thumb_max_height="" thumb_max_width="" imagepath="/" selectImage_root_folder="/" image_front_end_select="0" show_image_in_table="0" image_float="none" link_url="" my_table_data="id" update_on_edit="0" date_table_format="Y-m-d" date_form_format="%Y-%m-%d" date_showtime="0" date_defaulttotoday="0" database_join_display_type="dropdown" joinType="simple" join_conn_id="-1" join_db_name="" join_key_column="" join_val_column="" database_join_where_sql="" diysql="" database_join_noselectionvalue="" fabrikdatabasejoin_frontend_add="0" link_target="_self" view_access="1" show_in_rss_feed="0" show_label_in_rss_feed="0" use_as_fake_key="0" element_alt_table_heading="" icon_folder="-1" custom_link="" use_as_row_class="0" filter_access="1" full_words_only="0" inc_in_adv_search="1" sum_on="0" sum_access="1" sum_split="" avg_on="0" avg_access="1" avg_split="" median_on="0" median_access="1" median_split="" count_on="0" count_condition="" count_access="1" count_split="" can_order="0" sub_options="{}" parent_linked="1"/>
    </element>
    <element label="Result for" published="1" name="result_for" id="2419" plugin="databasejoin" created="2015-01-26 15:21:08" width="40" height="6" default="" hidden="1" eval="1" ordering="7" show_in_list_summary="1" filter_type="" filter_exact_match="0" link_to_detail="0" primary_key="0" auto_increment="0" access="1" use_in_page_title="0" parent_id="0">
      <params database_join_display_type="dropdown" max-width="" join_conn_id="1" join_db_name="jos_emundus_setup_campaigns" join_key_column="profile_id" join_val_column="label" join_val_column_concat="" database_join_where_sql="where id={jos_emundus_final_grade___campaign_id}" database_join_where_access="1" database_join_where_when="3" database_join_join_sql="" database_join_noselectionvalue="" database_join_noselectionlabel="" database_join_show_please_select="0" databasejoin_popupform="103" fabrikdatabasejoin_frontend_add="0" join_popupwidth="0" databasejoin_readonly_link="0" fabrikdatabasejoin_frontend_select="0" dabase_join_label_eval="" join_desc_column="description" dbjoin_options_per_row="4" dbjoin_multilist_size="6" dbjoin_autocomplete_size="20" dbjoin_autocomplete_how="contains" show_in_rss_feed="0" show_label_in_rss_feed="0" use_as_fake_key="0" use_as_rss_enclosure="0" rollover="" tipseval="0" tipsoverelement="0" tiplocation="top" labelindetails="1" labelinlist="0" comment="" view_access="1" view_access_user="" list_view_access="1" encrypt="0" can_order="0" alt_list_heading="" custom_link="" custom_link_indetails="1" use_as_row_class="0" include_in_list_query="1" always_render="0" icon_folder="0" icon_hovertext="1" icon_file="" filter_length="20" filter_access="1" full_words_only="0" filter_required="0" filter_build_method="0" filter_groupby="text" inc_in_adv_search="1" tablecss_header_class="" tablecss_header="" tablecss_cell_class="" tablecss_cell="" sum_on="0" sum_label="Sum" sum_access="1" sum_split="633" avg_on="0" avg_label="Average" avg_access="1" avg_round="0" avg_split="633" median_on="0" median_label="Median" median_access="1" median_split="633" count_on="0" count_label="Count" count_condition="" count_access="1" count_split="633" custom_calc_on="0" custom_calc_label="Custom" custom_calc_query="" custom_calc_access="8" custom_calc_split="" custom_calc_php="" validations="[]" parent_linked="1"/>
      <join table_join="jos_emundus_setup_campaigns" table_join_alias="" list_id="0" element_id="2419" join_from_table="" table_key="result_for" table_join_key="profile_id" join_type="left" group_id="230">
        <params join-label="label" type="element" pk="`jos_emundus_setup_campaigns`.`id`"/>
      </join>
    </element>
    <element label="Scholaship" published="0" name="scholarship" id="2420" plugin="databasejoin" created="2015-01-26 15:21:08" width="40" height="6" default="" hidden="0" eval="0" ordering="8" show_in_list_summary="0" filter_type="" filter_exact_match="0" link_to_detail="0" primary_key="0" auto_increment="0" access="1" use_in_page_title="0" parent_id="0">
      <params ck_value="" ck_default_label="" element_before_label="1" ck_options_per_row="4" allow_frontend_addtocheckbox="0" chk-allowadd-onlylabel="0" chk-savenewadditions="0" options_split_str="" database_join_display_type="dropdown" join_conn_id="1" join_db_name="jos_emundus_setup_scholarship" join_key_column="value" join_val_column="value" join_val_column_concat="" database_join_where_sql="order by ordering" database_join_where_access="0" database_join_where_when="3" database_join_noselectionvalue="No scholarship" database_join_noselectionlabel="No scholarship" database_join_show_please_select="1" fabrikdatabasejoin_frontend_add="0" yoffset="" join_popupwidth="" databasejoin_readonly_link="0" fabrikdatabasejoin_frontend_select="0" dabase_join_label_eval="" join_desc_column="" append_table_where="0" date_store_as_local="0" date_table_format="%Y-%m-%d" date_form_format="%Y-%m-%d" date_defaulttotoday="0" date_alwaystoday="0" date_firstday="0" date_allow_typing_in_field="1" date_csv_offset_tz="0" date_showtime="0" date_time_format="%H:%M" display_showlabel="1" multiple="0" dropdown_multisize="3" allow_frontend_addtodropdown="0" dd-allowadd-onlylabel="0" dd-savenewadditions="0" drd_initial_selection="" password="0" maxlength="255" text_format="text" integer_length="6" decimal_length="2" field_use_number_format="0" field_thousand_sep="," field_decimal_sep="." text_format_string="" guess_linktype="0" link_target_field="0" link_target_options="default" disable="0" readonly="0" autocomplete="1" ul_max_file_size="61440" ul_file_types="" ul_directory="" ul_email_file="0" random_filename="0" length_random_filename="" ul_file_increment="0" upload_allow_folderselect="0" upload_delete_image="1" default_image="" make_link="0" fu_show_image_in_table="0" fu_show_image="0" fu_show_image_in_email="0" image_library="gd2" fu_main_max_width="" fu_main_max_height="" fu_title_element="" make_thumbnail="0" thumb_dir="" thumb_prefix="" thumb_max_width="" thumb_max_height="" fu_make_pdf_thumb="0" fileupload_crop="0" fileupload_crop_dir="" fileupload_crop_width="" fileupload_crop_height="" fu_use_download_script="0" fu_download_acl="" fu_download_noaccess_image="" fu_download_access_image="" fu_download_email="" fu_download_hit_counter="" fu_download_log="0" fileupload_storage_type="filesystemstorage" fileupload_aws_accesskey="" fileupload_aws_secretkey="" fileupload_aws_location="" fileupload_aws_bucketname="" fileupload_ssl="0" fileupload_amazon_acl="2" fileupload_amazon_auth_url="" ul_export_encode_csv="relative" ul_export_encode_json="relative" imagepath="/" selectImage_root_folder="/" image_front_end_select="0" show_image_in_table="0" image_float="none" link_url="" link_default_url="http://" link_target="_self" link_smart_link="0" use_bitly="0" bitly_login="" bitly_apikey="" radio_element_before_label="0" options_per_row="4" allow_frontend_addtoradio="0" rad-allowadd-onlylabel="0" rad-savenewadditions="0" use_wysiwyg="0" textarea-showmax="0" textarea-maxlength="255" delete_overflow="1" textarea-tagify="0" textarea_tagifyurl="" textarea-truncate="0" textarea-hover="1" my_table_data="id" update_on_edit="0" update_on_copy="0" user_use_social_plugin_profile="0" user_noselectionlabel="" calc_calculation="" calc_format_string="" calc_on_save_only="0" calc_ajax="0" calc_ajax_observe="" ac_sql="" ac_callback_id="" ac_search_value_id="" ac_search_field="" ac_info_field="" ac_info_cible_id="" ac_format_string="" view_access="1" encrypt="0" show_in_rss_feed="0" show_label_in_rss_feed="0" use_as_fake_key="0" rollover="" hover_text_title="" tipsoverelement="0" labelindetails="1" comment="" element_alt_table_heading="" icon_folder="-1" custom_link="" use_as_row_class="0" filter_access="1" full_words_only="0" inc_in_adv_search="1" inc_in_search_all="1" filter_required="0" filter_build_method="0" filter_groupby="text" filter_length="20" tablecss_header_class="" tablecss_header="" tablecss_cell_class="" tablecss_cell="" sum_on="0" sum_label="Sum" sum_access="1" sum_split="" avg_on="0" avg_label="Average" avg_access="1" avg_split="" median_on="0" median_label="Median" median_access="1" median_split="" count_on="0" count_label="Count" count_condition="" count_access="1" count_split="" can_order="0" sub_options="{}" parent_linked="1"/>
      <join table_join="jos_emundus_setup_scholarship" table_join_alias="" list_id="0" element_id="2420" join_from_table="" table_key="scholarship" table_join_key="value" join_type="left" group_id="230">
        <params join-label="value" pk="`jos_emundus_setup_scholarship`.`id`"/>
      </join>
    </element>
    <element label="Info 1" published="1" name="info1" id="2421" plugin="textarea" created="2015-01-26 15:21:08" width="30" height="4" default="" hidden="0" eval="0" ordering="9" show_in_list_summary="0" filter_type="" filter_exact_match="0" link_to_detail="0" primary_key="0" auto_increment="0" access="1" use_in_page_title="0" parent_id="0">
      <params textarea_placeholder="" use_wysiwyg="0" textarea-showmax="0" textarea-maxlength="255" textarea_limit_type="char" textarea-tagify="0" textarea_tagifyurl="" textarea-truncate="0" textarea-hover="1" textarea_hover_location="top" show_in_rss_feed="0" show_label_in_rss_feed="0" use_as_fake_key="0" use_as_rss_enclosure="0" rollover="" tipseval="0" tipsoverelement="0" tiplocation="top" labelindetails="1" labelinlist="0" comment="" view_access="1" list_view_access="1" encrypt="0" can_order="0" alt_list_heading="" custom_link="" custom_link_indetails="1" use_as_row_class="0" include_in_list_query="1" always_render="0" icon_hovertext="1" icon_file="" filter_length="20" filter_access="1" full_words_only="0" filter_required="0" filter_build_method="0" filter_groupby="text" inc_in_adv_search="1" tablecss_header_class="" tablecss_header="" tablecss_cell_class="" tablecss_cell="" sum_on="0" sum_label="Sum" sum_access="1" sum_split="" avg_on="0" avg_label="Average" avg_access="1" avg_round="0" avg_split="" median_on="0" median_label="Median" median_access="1" median_split="" count_on="0" count_label="Count" count_condition="" count_access="1" count_split="" custom_calc_on="0" custom_calc_label="Custom" custom_calc_query="" custom_calc_access="8" custom_calc_split="" custom_calc_php="" validations="[]" parent_linked="1" textarea_showlabel="1" view_access_user="" icon_folder="0"/>
    </element>
    <element label="Info 2" published="1" name="info2" id="2422" plugin="textarea" created="2015-01-26 15:21:08" width="30" height="4" default="" hidden="0" eval="0" ordering="10" show_in_list_summary="0" filter_type="" filter_exact_match="0" link_to_detail="0" primary_key="0" auto_increment="0" access="1" use_in_page_title="0" parent_id="0">
      <params ck_value="" ck_default_label="" element_before_label="1" ck_options_per_row="4" allow_frontend_addtocheckbox="0" chk-allowadd-onlylabel="0" chk-savenewadditions="0" options_split_str="" database_join_display_type="dropdown" join_conn_id="1" join_db_name="" join_key_column="" join_val_column="" join_val_column_concat="" database_join_where_sql="" database_join_where_access="0" database_join_where_when="3" database_join_noselectionvalue="" database_join_noselectionlabel="" database_join_show_please_select="1" fabrikdatabasejoin_frontend_add="0" yoffset="" join_popupwidth="" databasejoin_readonly_link="0" fabrikdatabasejoin_frontend_select="0" dabase_join_label_eval="" join_desc_column="" append_table_where="0" dbjoin_options_per_row="4" date_store_as_local="0" date_table_format="%Y-%m-%d" date_form_format="%Y-%m-%d" date_defaulttotoday="0" date_alwaystoday="0" date_firstday="0" date_allow_typing_in_field="1" date_csv_offset_tz="0" date_showtime="0" date_time_format="%H:%M" display_showlabel="1" multiple="0" dropdown_multisize="3" allow_frontend_addtodropdown="0" dd-allowadd-onlylabel="0" dd-savenewadditions="0" drd_initial_selection="" password="0" maxlength="255" text_format="text" integer_length="6" decimal_length="2" field_use_number_format="0" field_thousand_sep="," field_decimal_sep="." text_format_string="" guess_linktype="0" link_target_options="default" disable="0" readonly="0" autocomplete="1" ul_max_file_size="61440" ul_file_types="" ul_directory="" ul_email_file="0" random_filename="0" length_random_filename="" ul_file_increment="0" upload_allow_folderselect="0" upload_delete_image="1" default_image="" make_link="0" fu_show_image_in_table="0" fu_show_image="0" fu_show_image_in_email="0" image_library="gd2" fu_main_max_width="" fu_main_max_height="" fu_title_element="" make_thumbnail="0" thumb_dir="" thumb_prefix="" thumb_max_width="" thumb_max_height="" fu_make_pdf_thumb="0" ajax_upload="0" ajax_runtime="html5" ajax_max="4" ajax_dropbox_width="300" ajax_dropbox_height="200" ajax_chunk_size="0" fileupload_crop="0" fileupload_crop_dir="" fileupload_crop_width="" fileupload_crop_height="" fileupload_crop_bg="#FFFFFF" fu_use_download_script="0" fu_download_acl="" fu_download_noaccess_image="" fu_download_noaccess_url="" fu_download_access_image="" fu_download_email="" fu_download_hit_counter="" fu_download_log="0" fileupload_storage_type="filesystemstorage" fileupload_aws_accesskey="" fileupload_aws_secretkey="" fileupload_aws_location="" fileupload_aws_bucketname="" fileupload_ssl="0" fileupload_amazon_acl="2" fileupload_skip_check="0" fileupload_amazon_auth_url="" ul_export_encode_csv="relative" ul_export_encode_json="relative" imagepath="/" selectImage_root_folder="/" image_front_end_select="0" show_image_in_table="0" image_float="none" link_url="" link_default_url="http://" link_target="_self" link_smart_link="0" link_attribs="" use_bitly="0" bitly_login="" bitly_apikey="" radio_element_before_label="0" options_per_row="4" allow_frontend_addtoradio="0" rad-allowadd-onlylabel="0" rad-savenewadditions="0" use_wysiwyg="0" textarea-showmax="0" textarea-maxlength="255" delete_overflow="1" textarea-tagify="0" textarea_tagifyurl="" textarea-truncate="0" textarea-hover="1" my_table_data="id" update_on_edit="0" update_on_copy="0" user_use_social_plugin_profile="0" user_noselectionlabel="" calc_calculation="" calc_format_string="" calc_on_save_only="0" calc_ajax="0" calc_ajax_observe="" ac_sql="" ac_callback_id="" ac_search_value_id="" ac_search_field="" ac_info_field="" ac_info_cible_id="" ac_format_string="" cascadingdropdown_connection="1" cascadingdropdown_table="" cascadingdropdown_id="-1" cascadingdropdown_label="-1" cascadingdropdown_label_concat="" cascadingdropdown_observe="" cascadingdropdown_key="-1" cascadingdropdown_filter="" cascadingdropdown_showpleaseselect="1" cascadingdropdown_readonly_link="0" cdd_desc_column="-1" view_access="1" encrypt="0" show_in_rss_feed="0" show_label_in_rss_feed="0" use_as_fake_key="0" rollover="" hover_text_title="" tipsoverelement="0" labelindetails="1" labelintable="0" comment="" element_alt_table_heading="" icon_folder="-1" custom_link="" use_as_row_class="0" filter_access="1" full_words_only="0" inc_in_adv_search="1" inc_in_search_all="1" filter_required="0" filter_build_method="0" filter_groupby="text" filter_length="20" tablecss_header_class="" tablecss_header="" tablecss_cell_class="" tablecss_cell="" sum_on="0" sum_label="Sum" sum_access="1" sum_split="" avg_on="0" avg_label="Average" avg_access="1" avg_split="" median_on="0" median_label="Median" median_access="1" median_split="" count_on="0" count_label="Count" count_condition="" count_access="1" count_split="" can_order="0" sub_options="{}" parent_linked="1"/>
    </element>
    <element label="Registration period" published="0" name="campaign_id" id="2423" plugin="databasejoin" created="2015-01-26 15:21:08" width="0" height="0" default="" hidden="1" eval="0" ordering="11" show_in_list_summary="0" filter_type="" filter_exact_match="1" link_to_detail="0" primary_key="0" auto_increment="0" access="1" use_in_page_title="0" parent_id="0">
      <params database_join_display_type="dropdown" max-width="" join_conn_id="1" join_db_name="jos_emundus_setup_campaigns" join_key_column="id" join_val_column="label" join_val_column_concat="" database_join_where_sql="where id={jos_emundus_final_grade___campaign_id}" database_join_where_access="1" database_join_where_when="3" database_join_join_sql="" database_join_noselectionvalue="" database_join_noselectionlabel="" database_join_show_please_select="0" databasejoin_popupform="103" fabrikdatabasejoin_frontend_add="0" join_popupwidth="0" databasejoin_readonly_link="0" fabrikdatabasejoin_frontend_select="0" dabase_join_label_eval="" join_desc_column="" dbjoin_options_per_row="4" dbjoin_multilist_size="6" dbjoin_autocomplete_size="20" dbjoin_autocomplete_how="contains" show_in_rss_feed="0" show_label_in_rss_feed="0" use_as_fake_key="0" use_as_rss_enclosure="0" rollover="" tipseval="0" tipsoverelement="0" tiplocation="top" labelindetails="1" labelinlist="0" comment="" view_access="1" view_access_user="" list_view_access="1" encrypt="0" can_order="0" alt_list_heading="" custom_link="" custom_link_indetails="1" use_as_row_class="0" include_in_list_query="1" always_render="0" icon_folder="0" icon_hovertext="1" icon_file="" filter_length="20" filter_access="1" full_words_only="0" filter_required="0" filter_build_method="0" filter_groupby="text" inc_in_adv_search="1" tablecss_header_class="" tablecss_header="" tablecss_cell_class="" tablecss_cell="" sum_on="0" sum_label="Sum" sum_access="8" sum_split="" avg_on="0" avg_label="Average" avg_access="8" avg_round="0" avg_split="" median_on="0" median_label="Median" median_access="8" median_split="" count_on="0" count_label="Count" count_condition="" count_access="8" count_split="" custom_calc_on="0" custom_calc_label="Custom" custom_calc_query="" custom_calc_access="8" custom_calc_split="" custom_calc_php="" notempty-message="[&quot;Can not be empty&quot;]" notempty-validation_condition="[&quot;&quot;]" validations="{&quot;plugin&quot;:[&quot;notempty&quot;],&quot;plugin_published&quot;:[&quot;1&quot;]}"/>
      <join table_join="jos_emundus_setup_campaigns" table_join_alias="" list_id="0" element_id="2423" join_from_table="" table_key="campaign_id" table_join_key="id" join_type="left" group_id="230">
        <params join-label="label" type="element" pk="`jos_emundus_setup_campaigns`.`id`"/>
      </join>
    </element>
    <element label="Lettre d&#x2019;admission envoy&#xE9;" published="1" name="admission_sent" id="2424" plugin="radiobutton" created="2015-01-26 15:23:25" width="0" height="0" default="" hidden="0" eval="0" ordering="12" show_in_list_summary="0" filter_type="" filter_exact_match="1" link_to_detail="0" primary_key="0" auto_increment="0" access="1" use_in_page_title="0" parent_id="0">
      <params sub_options="{&quot;sub_values&quot;:[&quot;1&quot;,&quot;0&quot;],&quot;sub_labels&quot;:[&quot;Oui&quot;,&quot;Non&quot;]}" radio_element_before_label="1" options_per_row="1" allow_frontend_addtoradio="0" rad-allowadd-onlylabel="0" rad-savenewadditions="0" show_in_rss_feed="0" show_label_in_rss_feed="0" use_as_fake_key="0" use_as_rss_enclosure="0" rollover="" tipseval="0" tipsoverelement="0" tiplocation="top" labelindetails="1" labelinlist="0" comment="" view_access="1" view_access_user="" list_view_access="1" encrypt="0" can_order="0" alt_list_heading="" custom_link="" custom_link_indetails="1" use_as_row_class="0" include_in_list_query="1" always_render="0" icon_folder="0" icon_hovertext="1" icon_file="" filter_length="20" filter_access="1" full_words_only="0" filter_required="0" filter_build_method="0" filter_groupby="text" inc_in_adv_search="1" tablecss_header_class="" tablecss_header="" tablecss_cell_class="" tablecss_cell="" sum_on="0" sum_label="Sum" sum_access="8" sum_split="" avg_on="0" avg_label="Average" avg_access="8" avg_round="0" avg_split="" median_on="0" median_label="Median" median_access="8" median_split="" count_on="0" count_label="Count" count_condition="" count_access="8" count_split="" custom_calc_on="0" custom_calc_label="Custom" custom_calc_query="" custom_calc_access="8" custom_calc_split="" custom_calc_php="" validations="[]"/>
    </element>
    <element label="Lettre d&#x2019;admission : date" published="1" name="admission_sent_date" id="2426" plugin="date" created="2015-01-26 15:24:32" width="10" height="0" default="" hidden="0" eval="0" ordering="13" show_in_list_summary="0" filter_type="" filter_exact_match="1" link_to_detail="0" primary_key="0" auto_increment="0" access="1" use_in_page_title="0" parent_id="0">
      <params date_store_as_local="0" date_table_format="%d/%m/%Y" date_form_format="%d/%m/%Y" date_defaulttotoday="0" date_alwaystoday="0" date_firstday="0" date_allow_typing_in_field="1" date_csv_offset_tz="0" date_showtime="0" date_time_format="%H:%M" date_advanced="0" date_allow_func="" show_in_rss_feed="0" show_label_in_rss_feed="0" use_as_fake_key="0" use_as_rss_enclosure="0" rollover="" tipseval="0" tipsoverelement="0" tiplocation="top" labelindetails="1" labelinlist="0" comment="" view_access="1" view_access_user="" list_view_access="1" encrypt="0" can_order="0" alt_list_heading="" custom_link="" custom_link_indetails="1" use_as_row_class="0" include_in_list_query="1" always_render="0" icon_folder="0" icon_hovertext="1" icon_file="" filter_length="20" filter_access="1" full_words_only="0" filter_required="0" filter_build_method="0" filter_groupby="text" inc_in_adv_search="1" tablecss_header_class="" tablecss_header="" tablecss_cell_class="" tablecss_cell="" sum_on="0" sum_label="Sum" sum_access="8" sum_split="" avg_on="0" avg_label="Average" avg_access="8" avg_round="0" avg_split="" median_on="0" median_label="Median" median_access="8" median_split="" count_on="0" count_label="Count" count_condition="" count_access="8" count_split="" custom_calc_on="0" custom_calc_label="Custom" custom_calc_query="" custom_calc_access="8" custom_calc_split="" custom_calc_php="" validations="[]"/>
    </element>
    <element label="Inscription confirm&#xE9;e par l&#x2019;&#xE9;tudiant" published="1" name="engaged" id="2417" plugin="radiobutton" created="2015-01-26 15:21:08" width="40" height="6" default="" hidden="0" eval="0" ordering="14" show_in_list_summary="1" filter_type="" filter_exact_match="0" link_to_detail="0" primary_key="0" auto_increment="0" access="1" use_in_page_title="0" parent_id="0">
      <params sub_options="{&quot;sub_values&quot;:[&quot;1&quot;,&quot;0&quot;],&quot;sub_labels&quot;:[&quot;Oui&quot;,&quot;Non&quot;],&quot;sub_initial_selection&quot;:[&quot;0&quot;]}" radio_element_before_label="1" options_per_row="1" allow_frontend_addtoradio="0" rad-allowadd-onlylabel="0" rad-savenewadditions="0" show_in_rss_feed="0" show_label_in_rss_feed="0" use_as_fake_key="0" use_as_rss_enclosure="0" rollover="" tipseval="0" tipsoverelement="0" tiplocation="top" labelindetails="1" labelinlist="0" comment="" view_access="1" view_access_user="" list_view_access="1" encrypt="0" can_order="0" alt_list_heading="" custom_link="" custom_link_indetails="1" use_as_row_class="0" include_in_list_query="1" always_render="0" icon_folder="0" icon_hovertext="1" icon_file="" filter_length="20" filter_access="1" full_words_only="0" filter_required="0" filter_build_method="0" filter_groupby="text" inc_in_adv_search="1" tablecss_header_class="" tablecss_header="" tablecss_cell_class="" tablecss_cell="" sum_on="0" sum_label="Sum" sum_access="1" sum_split="" avg_on="0" avg_label="Average" avg_access="1" avg_round="0" avg_split="" median_on="0" median_label="Median" median_access="1" median_split="" count_on="0" count_label="Count" count_condition="" count_access="1" count_split="" custom_calc_on="0" custom_calc_label="Custom" custom_calc_query="" custom_calc_access="8" custom_calc_split="" custom_calc_php="" validations="[]"/>
    </element>
    <element label="Entretien de v&#xE9;rification du niveau de Fran&#xE7;ais effectu&#xE9;" published="1" name="interview_done" id="2428" plugin="radiobutton" created="2015-01-26 15:26:52" width="0" height="0" default="" hidden="0" eval="0" ordering="15" show_in_list_summary="0" filter_type="" filter_exact_match="1" link_to_detail="0" primary_key="0" auto_increment="0" access="1" use_in_page_title="0" parent_id="0">
      <params sub_options="{&quot;sub_values&quot;:[&quot;1&quot;,&quot;0&quot;,&quot;2&quot;],&quot;sub_labels&quot;:[&quot;Oui&quot;,&quot;Non&quot;,&quot;Pas d'entretien pr\u00e9vu&quot;]}" radio_element_before_label="1" options_per_row="1" allow_frontend_addtoradio="0" rad-allowadd-onlylabel="0" rad-savenewadditions="0" show_in_rss_feed="0" show_label_in_rss_feed="0" use_as_fake_key="0" use_as_rss_enclosure="0" rollover="" tipseval="0" tipsoverelement="0" tiplocation="top" labelindetails="1" labelinlist="0" comment="" view_access="1" view_access_user="" list_view_access="1" encrypt="0" can_order="0" alt_list_heading="" custom_link="" custom_link_indetails="1" use_as_row_class="0" include_in_list_query="1" always_render="0" icon_folder="0" icon_hovertext="1" icon_file="" filter_length="20" filter_access="1" full_words_only="0" filter_required="0" filter_build_method="0" filter_groupby="text" inc_in_adv_search="1" tablecss_header_class="" tablecss_header="" tablecss_cell_class="" tablecss_cell="" sum_on="0" sum_label="Sum" sum_access="8" sum_split="" avg_on="0" avg_label="Average" avg_access="8" avg_round="0" avg_split="" median_on="0" median_label="Median" median_access="8" median_split="" count_on="0" count_label="Count" count_condition="" count_access="8" count_split="" custom_calc_on="0" custom_calc_label="Custom" custom_calc_query="" custom_calc_access="8" custom_calc_split="" custom_calc_php="" validations="[]"/>
    </element>
    <element label="Acompte vers&#xE9;" published="1" name="account_paid" id="2430" plugin="radiobutton" created="2015-01-26 15:27:26" width="0" height="0" default="" hidden="0" eval="0" ordering="16" show_in_list_summary="0" filter_type="" filter_exact_match="1" link_to_detail="0" primary_key="0" auto_increment="0" access="1" use_in_page_title="0" parent_id="0">
      <params sub_options="{&quot;sub_values&quot;:[&quot;1&quot;,&quot;0&quot;,&quot;-1&quot;],&quot;sub_labels&quot;:[&quot;Oui&quot;,&quot;Non&quot;,&quot;Dispens\u00e9 d'acompte&quot;]}" radio_element_before_label="1" options_per_row="1" allow_frontend_addtoradio="0" rad-allowadd-onlylabel="0" rad-savenewadditions="0" show_in_rss_feed="0" show_label_in_rss_feed="0" use_as_fake_key="0" use_as_rss_enclosure="0" rollover="" tipseval="0" tipsoverelement="0" tiplocation="top" labelindetails="1" labelinlist="0" comment="" view_access="1" view_access_user="" list_view_access="1" encrypt="0" can_order="0" alt_list_heading="" custom_link="" custom_link_indetails="1" use_as_row_class="0" include_in_list_query="1" always_render="0" icon_folder="0" icon_hovertext="1" icon_file="" filter_length="20" filter_access="1" full_words_only="0" filter_required="0" filter_build_method="0" filter_groupby="text" inc_in_adv_search="1" tablecss_header_class="" tablecss_header="" tablecss_cell_class="" tablecss_cell="" sum_on="0" sum_label="Sum" sum_access="8" sum_split="" avg_on="0" avg_label="Average" avg_access="8" avg_round="0" avg_split="" median_on="0" median_label="Median" median_access="8" median_split="" count_on="0" count_label="Count" count_condition="" count_access="8" count_split="" custom_calc_on="0" custom_calc_label="Custom" custom_calc_query="" custom_calc_access="8" custom_calc_split="" custom_calc_php="" validations="[]"/>
    </element>
    <element label="Date et heure d&#x2019;arriv&#xE9;e &#xE0; Angers" published="1" name="date_arrive" id="2432" plugin="date" created="2015-01-26 15:29:58" width="10" height="0" default="" hidden="0" eval="0" ordering="17" show_in_list_summary="0" filter_type="" filter_exact_match="1" link_to_detail="0" primary_key="0" auto_increment="0" access="1" use_in_page_title="0" parent_id="0">
      <params date_store_as_local="0" date_table_format="%d/%m/%Y" date_form_format="%d/%m/%Y" date_defaulttotoday="0" date_alwaystoday="0" date_firstday="0" date_allow_typing_in_field="1" date_csv_offset_tz="0" date_showtime="1" date_time_format="%H:%M" date_advanced="0" date_allow_func="" show_in_rss_feed="0" show_label_in_rss_feed="0" use_as_fake_key="0" use_as_rss_enclosure="0" rollover="" tipseval="0" tipsoverelement="0" tiplocation="top" labelindetails="1" labelinlist="0" comment="" view_access="1" view_access_user="" list_view_access="1" encrypt="0" can_order="0" alt_list_heading="" custom_link="" custom_link_indetails="1" use_as_row_class="0" include_in_list_query="1" always_render="0" icon_folder="0" icon_hovertext="1" icon_file="" filter_length="20" filter_access="1" full_words_only="0" filter_required="0" filter_build_method="0" filter_groupby="text" inc_in_adv_search="1" tablecss_header_class="" tablecss_header="" tablecss_cell_class="" tablecss_cell="" sum_on="0" sum_label="Sum" sum_access="8" sum_split="" avg_on="0" avg_label="Average" avg_access="8" avg_round="0" avg_split="" median_on="0" median_label="Median" median_access="8" median_split="" count_on="0" count_label="Count" count_condition="" count_access="8" count_split="" custom_calc_on="0" custom_calc_label="Custom" custom_calc_query="" custom_calc_access="8" custom_calc_split="" custom_calc_php="" validations="[]"/>
    </element>
    <element label="Logement demand&#xE9;" published="1" name="flat_request" id="2434" plugin="radiobutton" created="2015-01-26 15:30:27" width="0" height="0" default="" hidden="0" eval="0" ordering="18" show_in_list_summary="0" filter_type="" filter_exact_match="1" link_to_detail="0" primary_key="0" auto_increment="0" access="1" use_in_page_title="0" parent_id="0">
      <params sub_options="{&quot;sub_values&quot;:[&quot;1&quot;,&quot;0&quot;],&quot;sub_labels&quot;:[&quot;Oui&quot;,&quot;Non&quot;]}" radio_element_before_label="1" options_per_row="1" allow_frontend_addtoradio="0" rad-allowadd-onlylabel="0" rad-savenewadditions="0" show_in_rss_feed="0" show_label_in_rss_feed="0" use_as_fake_key="0" use_as_rss_enclosure="0" rollover="" tipseval="0" tipsoverelement="0" tiplocation="top" labelindetails="1" labelinlist="0" comment="" view_access="1" view_access_user="" list_view_access="1" encrypt="0" can_order="0" alt_list_heading="" custom_link="" custom_link_indetails="1" use_as_row_class="0" include_in_list_query="1" always_render="0" icon_folder="0" icon_hovertext="1" icon_file="" filter_length="20" filter_access="1" full_words_only="0" filter_required="0" filter_build_method="0" filter_groupby="text" inc_in_adv_search="1" tablecss_header_class="" tablecss_header="" tablecss_cell_class="" tablecss_cell="" sum_on="0" sum_label="Sum" sum_access="8" sum_split="" avg_on="0" avg_label="Average" avg_access="8" avg_round="0" avg_split="" median_on="0" median_label="Median" median_access="8" median_split="" count_on="0" count_label="Count" count_condition="" count_access="8" count_split="" custom_calc_on="0" custom_calc_label="Custom" custom_calc_query="" custom_calc_access="8" custom_calc_split="" custom_calc_php="" validations="[]"/>
    </element>
    <element label="Logement coordonn&#xE9;es" published="1" name="flat_address" id="2436" plugin="textarea" created="2015-01-26 15:31:00" width="60" height="6" default="" hidden="0" eval="0" ordering="19" show_in_list_summary="0" filter_type="" filter_exact_match="1" link_to_detail="0" primary_key="0" auto_increment="0" access="1" use_in_page_title="0" parent_id="0">
      <params textarea_showlabel="1" textarea_placeholder="" use_wysiwyg="0" textarea-showmax="0" textarea-maxlength="255" textarea_limit_type="char" textarea-tagify="0" textarea_tagifyurl="" textarea-truncate="0" textarea-hover="1" textarea_hover_location="top" show_in_rss_feed="0" show_label_in_rss_feed="0" use_as_fake_key="0" use_as_rss_enclosure="0" rollover="" tipseval="0" tipsoverelement="0" tiplocation="top" labelindetails="1" labelinlist="0" comment="" view_access="1" view_access_user="" list_view_access="1" encrypt="0" can_order="0" alt_list_heading="" custom_link="" custom_link_indetails="1" use_as_row_class="0" include_in_list_query="1" always_render="0" icon_folder="0" icon_hovertext="1" icon_file="" filter_length="20" filter_access="1" full_words_only="0" filter_required="0" filter_build_method="0" filter_groupby="text" inc_in_adv_search="1" tablecss_header_class="" tablecss_header="" tablecss_cell_class="" tablecss_cell="" sum_on="0" sum_label="Sum" sum_access="8" sum_split="" avg_on="0" avg_label="Average" avg_access="8" avg_round="0" avg_split="" median_on="0" median_label="Median" median_access="8" median_split="" count_on="0" count_label="Count" count_condition="" count_access="8" count_split="" custom_calc_on="0" custom_calc_label="Custom" custom_calc_query="" custom_calc_access="8" custom_calc_split="" custom_calc_php="" validations="[]"/>
    </element>
    <element label="Cidef" published="1" name="cidef" id="2438" plugin="radiobutton" created="2015-01-26 15:31:31" width="0" height="0" default="" hidden="0" eval="0" ordering="20" show_in_list_summary="0" filter_type="" filter_exact_match="1" link_to_detail="0" primary_key="0" auto_increment="0" access="1" use_in_page_title="0" parent_id="0">
      <params sub_options="{&quot;sub_values&quot;:[&quot;1&quot;,&quot;0&quot;],&quot;sub_labels&quot;:[&quot;Oui&quot;,&quot;Non&quot;]}" radio_element_before_label="1" options_per_row="1" allow_frontend_addtoradio="0" rad-allowadd-onlylabel="0" rad-savenewadditions="0" show_in_rss_feed="0" show_label_in_rss_feed="0" use_as_fake_key="0" use_as_rss_enclosure="0" rollover="" tipseval="0" tipsoverelement="0" tiplocation="top" labelindetails="1" labelinlist="0" comment="" view_access="1" view_access_user="" list_view_access="1" encrypt="0" can_order="0" alt_list_heading="" custom_link="" custom_link_indetails="1" use_as_row_class="0" include_in_list_query="1" always_render="0" icon_folder="0" icon_hovertext="1" icon_file="" filter_length="20" filter_access="1" full_words_only="0" filter_required="0" filter_build_method="0" filter_groupby="text" inc_in_adv_search="1" tablecss_header_class="" tablecss_header="" tablecss_cell_class="" tablecss_cell="" sum_on="0" sum_label="Sum" sum_access="8" sum_split="" avg_on="0" avg_label="Average" avg_access="8" avg_round="0" avg_split="" median_on="0" median_label="Median" median_access="8" median_split="" count_on="0" count_label="Count" count_condition="" count_access="8" count_split="" custom_calc_on="0" custom_calc_label="Custom" custom_calc_query="" custom_calc_access="8" custom_calc_split="" custom_calc_php="" validations="[]"/>
    </element>
    <element label="Cidef : dates" published="1" name="cidef_date" id="2440" plugin="date" created="2015-01-26 15:32:06" width="10" height="0" default="" hidden="0" eval="0" ordering="21" show_in_list_summary="0" filter_type="" filter_exact_match="1" link_to_detail="0" primary_key="0" auto_increment="0" access="1" use_in_page_title="0" parent_id="0">
      <params date_store_as_local="0" date_table_format="%d/%m/%Y" date_form_format="%d/%m/%Y" date_defaulttotoday="0" date_alwaystoday="0" date_firstday="0" date_allow_typing_in_field="1" date_csv_offset_tz="0" date_showtime="0" date_time_format="%H:%M" date_advanced="0" date_allow_func="" show_in_rss_feed="0" show_label_in_rss_feed="0" use_as_fake_key="0" use_as_rss_enclosure="0" rollover="" tipseval="0" tipsoverelement="0" tiplocation="top" labelindetails="1" labelinlist="0" comment="" view_access="1" view_access_user="" list_view_access="1" encrypt="0" can_order="0" alt_list_heading="" custom_link="" custom_link_indetails="1" use_as_row_class="0" include_in_list_query="1" always_render="0" icon_folder="0" icon_hovertext="1" icon_file="" filter_length="20" filter_access="1" full_words_only="0" filter_required="0" filter_build_method="0" filter_groupby="text" inc_in_adv_search="1" tablecss_header_class="" tablecss_header="" tablecss_cell_class="" tablecss_cell="" sum_on="0" sum_label="Sum" sum_access="8" sum_split="" avg_on="0" avg_label="Average" avg_access="8" avg_round="0" avg_split="" median_on="0" median_label="Median" median_access="8" median_split="" count_on="0" count_label="Count" count_condition="" count_access="8" count_split="" custom_calc_on="0" custom_calc_label="Custom" custom_calc_query="" custom_calc_access="8" custom_calc_split="" custom_calc_php="" validations="[]"/>
    </element>
    <element label="Cidef : dates de fin" published="1" name="cidef_date_fin" id="2454" plugin="date" created="2015-01-27 10:28:26" width="10" height="0" default="" hidden="0" eval="0" ordering="22" show_in_list_summary="0" filter_type="" filter_exact_match="1" link_to_detail="0" primary_key="0" auto_increment="0" access="1" use_in_page_title="0" parent_id="0">
      <params date_store_as_local="0" date_table_format="%d/%m/%Y" date_form_format="%d/%m/%Y" date_defaulttotoday="0" date_alwaystoday="0" date_firstday="0" date_allow_typing_in_field="1" date_csv_offset_tz="0" date_showtime="0" date_time_format="%H:%M" date_advanced="0" date_allow_func="" show_in_rss_feed="0" show_label_in_rss_feed="0" use_as_fake_key="0" use_as_rss_enclosure="0" rollover="" tipseval="0" tipsoverelement="0" tiplocation="top" labelindetails="1" labelinlist="0" comment="" view_access="1" view_access_user="" list_view_access="1" encrypt="0" can_order="0" alt_list_heading="" custom_link="" custom_link_indetails="1" use_as_row_class="0" include_in_list_query="1" always_render="0" icon_folder="0" icon_hovertext="1" icon_file="" filter_length="20" filter_access="1" full_words_only="0" filter_required="0" filter_build_method="0" filter_groupby="text" inc_in_adv_search="1" tablecss_header_class="" tablecss_header="" tablecss_cell_class="" tablecss_cell="" sum_on="0" sum_label="Sum" sum_access="8" sum_split="" avg_on="0" avg_label="Average" avg_access="8" avg_round="0" avg_split="" median_on="0" median_label="Median" median_access="8" median_split="" count_on="0" count_label="Count" count_condition="" count_access="8" count_split="" custom_calc_on="0" custom_calc_label="Custom" custom_calc_query="" custom_calc_access="8" custom_calc_split="" custom_calc_php="" validations="[]"/>
    </element>
    <element label="Stage exploitation" published="1" name="stage" id="2442" plugin="radiobutton" created="2015-01-26 15:32:33" width="0" height="0" default="" hidden="0" eval="0" ordering="23" show_in_list_summary="0" filter_type="" filter_exact_match="1" link_to_detail="0" primary_key="0" auto_increment="0" access="1" use_in_page_title="0" parent_id="0">
      <params sub_options="{&quot;sub_values&quot;:[&quot;1&quot;,&quot;0&quot;],&quot;sub_labels&quot;:[&quot;Oui&quot;,&quot;Non&quot;]}" radio_element_before_label="1" options_per_row="1" allow_frontend_addtoradio="0" rad-allowadd-onlylabel="0" rad-savenewadditions="0" show_in_rss_feed="0" show_label_in_rss_feed="0" use_as_fake_key="0" use_as_rss_enclosure="0" rollover="" tipseval="0" tipsoverelement="0" tiplocation="top" labelindetails="1" labelinlist="0" comment="" view_access="1" view_access_user="" list_view_access="1" encrypt="0" can_order="0" alt_list_heading="" custom_link="" custom_link_indetails="1" use_as_row_class="0" include_in_list_query="1" always_render="0" icon_folder="0" icon_hovertext="1" icon_file="" filter_length="20" filter_access="1" full_words_only="0" filter_required="0" filter_build_method="0" filter_groupby="text" inc_in_adv_search="1" tablecss_header_class="" tablecss_header="" tablecss_cell_class="" tablecss_cell="" sum_on="0" sum_label="Sum" sum_access="8" sum_split="" avg_on="0" avg_label="Average" avg_access="8" avg_round="0" avg_split="" median_on="0" median_label="Median" median_access="8" median_split="" count_on="0" count_label="Count" count_condition="" count_access="8" count_split="" custom_calc_on="0" custom_calc_label="Custom" custom_calc_query="" custom_calc_access="8" custom_calc_split="" custom_calc_php="" validations="[]"/>
    </element>
    <element label="Stage exploitation &#x2013; dates" published="1" name="stage_date" id="2444" plugin="date" created="2015-01-26 15:33:15" width="10" height="0" default="" hidden="0" eval="0" ordering="24" show_in_list_summary="0" filter_type="" filter_exact_match="1" link_to_detail="0" primary_key="0" auto_increment="0" access="1" use_in_page_title="0" parent_id="0">
      <params date_store_as_local="0" date_table_format="%d/%m/%Y" date_form_format="%d/%m/%Y" date_defaulttotoday="0" date_alwaystoday="0" date_firstday="0" date_allow_typing_in_field="1" date_csv_offset_tz="0" date_showtime="0" date_time_format="%H:%M" date_advanced="0" date_allow_func="" show_in_rss_feed="0" show_label_in_rss_feed="0" use_as_fake_key="0" use_as_rss_enclosure="0" rollover="" tipseval="0" tipsoverelement="0" tiplocation="top" labelindetails="1" labelinlist="0" comment="" view_access="1" view_access_user="" list_view_access="1" encrypt="0" can_order="0" alt_list_heading="" custom_link="" custom_link_indetails="1" use_as_row_class="0" include_in_list_query="1" always_render="0" icon_folder="0" icon_hovertext="1" icon_file="" filter_length="20" filter_access="1" full_words_only="0" filter_required="0" filter_build_method="0" filter_groupby="text" inc_in_adv_search="1" tablecss_header_class="" tablecss_header="" tablecss_cell_class="" tablecss_cell="" sum_on="0" sum_label="Sum" sum_access="8" sum_split="" avg_on="0" avg_label="Average" avg_access="8" avg_round="0" avg_split="" median_on="0" median_label="Median" median_access="8" median_split="" count_on="0" count_label="Count" count_condition="" count_access="8" count_split="" custom_calc_on="0" custom_calc_label="Custom" custom_calc_query="" custom_calc_access="8" custom_calc_split="" custom_calc_php="" validations="[]"/>
    </element>
    <element label="Fle 1" published="1" name="fle1" id="2446" plugin="radiobutton" created="2015-01-26 15:33:44" width="0" height="0" default="" hidden="0" eval="0" ordering="25" show_in_list_summary="0" filter_type="" filter_exact_match="1" link_to_detail="0" primary_key="0" auto_increment="0" access="1" use_in_page_title="0" parent_id="0">
      <params sub_options="{&quot;sub_values&quot;:[&quot;1&quot;,&quot;0&quot;],&quot;sub_labels&quot;:[&quot;Oui&quot;,&quot;Non&quot;]}" radio_element_before_label="1" options_per_row="1" allow_frontend_addtoradio="0" rad-allowadd-onlylabel="0" rad-savenewadditions="0" show_in_rss_feed="0" show_label_in_rss_feed="0" use_as_fake_key="0" use_as_rss_enclosure="0" rollover="" tipseval="0" tipsoverelement="0" tiplocation="top" labelindetails="1" labelinlist="0" comment="" view_access="1" view_access_user="" list_view_access="1" encrypt="0" can_order="0" alt_list_heading="" custom_link="" custom_link_indetails="1" use_as_row_class="0" include_in_list_query="1" always_render="0" icon_folder="0" icon_hovertext="1" icon_file="" filter_length="20" filter_access="1" full_words_only="0" filter_required="0" filter_build_method="0" filter_groupby="text" inc_in_adv_search="1" tablecss_header_class="" tablecss_header="" tablecss_cell_class="" tablecss_cell="" sum_on="0" sum_label="Sum" sum_access="8" sum_split="" avg_on="0" avg_label="Average" avg_access="8" avg_round="0" avg_split="" median_on="0" median_label="Median" median_access="8" median_split="" count_on="0" count_label="Count" count_condition="" count_access="8" count_split="" custom_calc_on="0" custom_calc_label="Custom" custom_calc_query="" custom_calc_access="8" custom_calc_split="" custom_calc_php="" validations="[]"/>
    </element>
    <element label="FLe 1 &#x2013; dates" published="1" name="fle1_date" id="2448" plugin="date" created="2015-01-26 16:38:53" width="10" height="0" default="" hidden="0" eval="0" ordering="26" show_in_list_summary="0" filter_type="" filter_exact_match="1" link_to_detail="0" primary_key="0" auto_increment="0" access="1" use_in_page_title="0" parent_id="0">
      <params date_store_as_local="0" date_table_format="%d/%m/%Y" date_form_format="%d/%m/%Y" date_defaulttotoday="0" date_alwaystoday="0" date_firstday="0" date_allow_typing_in_field="1" date_csv_offset_tz="0" date_showtime="0" date_time_format="%H:%M" date_advanced="0" date_allow_func="" show_in_rss_feed="0" show_label_in_rss_feed="0" use_as_fake_key="0" use_as_rss_enclosure="0" rollover="" tipseval="0" tipsoverelement="0" tiplocation="top" labelindetails="1" labelinlist="0" comment="" view_access="1" view_access_user="" list_view_access="1" encrypt="0" can_order="0" alt_list_heading="" custom_link="" custom_link_indetails="1" use_as_row_class="0" include_in_list_query="1" always_render="0" icon_folder="0" icon_hovertext="1" icon_file="" filter_length="20" filter_access="1" full_words_only="0" filter_required="0" filter_build_method="0" filter_groupby="text" inc_in_adv_search="1" tablecss_header_class="" tablecss_header="" tablecss_cell_class="" tablecss_cell="" sum_on="0" sum_label="Sum" sum_access="8" sum_split="" avg_on="0" avg_label="Average" avg_access="8" avg_round="0" avg_split="" median_on="0" median_label="Median" median_access="8" median_split="" count_on="0" count_label="Count" count_condition="" count_access="8" count_split="" custom_calc_on="0" custom_calc_label="Custom" custom_calc_query="" custom_calc_access="8" custom_calc_split="" custom_calc_php="" validations="[]"/>
    </element>
    <element label="FLe 1 &#x2013; dates de fin" published="1" name="fle1_date_fin" id="2456" plugin="date" created="2015-01-27 10:29:10" width="10" height="0" default="" hidden="0" eval="0" ordering="27" show_in_list_summary="0" filter_type="" filter_exact_match="1" link_to_detail="0" primary_key="0" auto_increment="0" access="1" use_in_page_title="0" parent_id="0">
      <params date_store_as_local="0" date_table_format="%d/%m/%Y" date_form_format="%d/%m/%Y" date_defaulttotoday="0" date_alwaystoday="0" date_firstday="0" date_allow_typing_in_field="1" date_csv_offset_tz="0" date_showtime="0" date_time_format="%H:%M" date_advanced="0" date_allow_func="" show_in_rss_feed="0" show_label_in_rss_feed="0" use_as_fake_key="0" use_as_rss_enclosure="0" rollover="" tipseval="0" tipsoverelement="0" tiplocation="top" labelindetails="1" labelinlist="0" comment="" view_access="1" view_access_user="" list_view_access="1" encrypt="0" can_order="0" alt_list_heading="" custom_link="" custom_link_indetails="1" use_as_row_class="0" include_in_list_query="1" always_render="0" icon_folder="0" icon_hovertext="1" icon_file="" filter_length="20" filter_access="1" full_words_only="0" filter_required="0" filter_build_method="0" filter_groupby="text" inc_in_adv_search="1" tablecss_header_class="" tablecss_header="" tablecss_cell_class="" tablecss_cell="" sum_on="0" sum_label="Sum" sum_access="8" sum_split="" avg_on="0" avg_label="Average" avg_access="8" avg_round="0" avg_split="" median_on="0" median_label="Median" median_access="8" median_split="" count_on="0" count_label="Count" count_condition="" count_access="8" count_split="" custom_calc_on="0" custom_calc_label="Custom" custom_calc_query="" custom_calc_access="8" custom_calc_split="" custom_calc_php="" validations="[]"/>
    </element>
    <element label="Date d&#xE9;but cours Master" published="1" name="date_debut_master" id="2450" plugin="date" created="2015-01-26 16:42:59" width="10" height="0" default="" hidden="0" eval="0" ordering="28" show_in_list_summary="0" filter_type="" filter_exact_match="1" link_to_detail="0" primary_key="0" auto_increment="0" access="1" use_in_page_title="0" parent_id="0">
      <params date_store_as_local="0" date_table_format="%d/%m/%Y" date_form_format="%d/%m/%Y" date_defaulttotoday="0" date_alwaystoday="0" date_firstday="0" date_allow_typing_in_field="1" date_csv_offset_tz="0" date_showtime="0" date_time_format="%H:%M" date_advanced="0" date_allow_func="" show_in_rss_feed="0" show_label_in_rss_feed="0" use_as_fake_key="0" use_as_rss_enclosure="0" rollover="" tipseval="0" tipsoverelement="0" tiplocation="top" labelindetails="1" labelinlist="0" comment="" view_access="1" view_access_user="" list_view_access="1" encrypt="0" can_order="0" alt_list_heading="" custom_link="" custom_link_indetails="1" use_as_row_class="0" include_in_list_query="1" always_render="0" icon_folder="0" icon_hovertext="1" icon_file="" filter_length="20" filter_access="1" full_words_only="0" filter_required="0" filter_build_method="0" filter_groupby="text" inc_in_adv_search="1" tablecss_header_class="" tablecss_header="" tablecss_cell_class="" tablecss_cell="" sum_on="0" sum_label="Sum" sum_access="8" sum_split="" avg_on="0" avg_label="Average" avg_access="8" avg_round="0" avg_split="" median_on="0" median_label="Median" median_access="8" median_split="" count_on="0" count_label="Count" count_condition="" count_access="8" count_split="" custom_calc_on="0" custom_calc_label="Custom" custom_calc_query="" custom_calc_access="8" custom_calc_split="" custom_calc_php="" validations="[]"/>
    </element>
    <element label="Observations" published="1" name="observations" id="2452" plugin="textarea" created="2015-01-26 16:43:20" width="60" height="6" default="" hidden="0" eval="0" ordering="29" show_in_list_summary="0" filter_type="" filter_exact_match="1" link_to_detail="0" primary_key="0" auto_increment="0" access="1" use_in_page_title="0" parent_id="0">
      <params textarea_showlabel="1" textarea_placeholder="" use_wysiwyg="0" textarea-showmax="0" textarea-maxlength="255" textarea_limit_type="char" textarea-tagify="0" textarea_tagifyurl="" textarea-truncate="0" textarea-hover="1" textarea_hover_location="top" show_in_rss_feed="0" show_label_in_rss_feed="0" use_as_fake_key="0" use_as_rss_enclosure="0" rollover="" tipseval="0" tipsoverelement="0" tiplocation="top" labelindetails="1" labelinlist="0" comment="" view_access="1" view_access_user="" list_view_access="1" encrypt="0" can_order="0" alt_list_heading="" custom_link="" custom_link_indetails="1" use_as_row_class="0" include_in_list_query="1" always_render="0" icon_folder="0" icon_hovertext="1" icon_file="" filter_length="20" filter_access="1" full_words_only="0" filter_required="0" filter_build_method="0" filter_groupby="text" inc_in_adv_search="1" tablecss_header_class="" tablecss_header="" tablecss_cell_class="" tablecss_cell="" sum_on="0" sum_label="Sum" sum_access="8" sum_split="" avg_on="0" avg_label="Average" avg_access="8" avg_round="0" avg_split="" median_on="0" median_label="Median" median_access="8" median_split="" count_on="0" count_label="Count" count_condition="" count_access="8" count_split="" custom_calc_on="0" custom_calc_label="Custom" custom_calc_query="" custom_calc_access="8" custom_calc_split="" custom_calc_php="" validations="[]"/>
    </element>
  </group>
  <database>
    <source>jos_emundus_final_grade</source>
    <table_structure name="#__emundus_setup_campaigns">
   <field Field="id" Type="int(11)" Null="NO" Key="PRI" Extra="auto_increment"/>
   <field Field="date_time" Type="timestamp" Null="NO" Key="" Default="CURRENT_TIMESTAMP" Extra=""/>
   <field Field="user" Type="int(11)" Null="YES" Key="MUL" Extra=""/>
   <field Field="label" Type="varchar(255)" Null="YES" Key="MUL" Extra=""/>
   <field Field="description" Type="text" Null="YES" Key="" Extra=""/>
   <field Field="start_date" Type="datetime" Null="YES" Key="MUL" Extra=""/>
   <field Field="end_date" Type="datetime" Null="YES" Key="MUL" Extra=""/>
   <field Field="profile_id" Type="int(11)" Null="YES" Key="MUL" Extra=""/>
   <field Field="training" Type="varchar(255)" Null="YES" Key="MUL" Extra=""/>
   <field Field="year" Type="varchar(20)" Null="YES" Key="MUL" Extra=""/>
   <field Field="published" Type="text" Null="YES" Key="MUL" Extra=""/>
   <field Field="short_description" Type="text" Null="NO" Key="" Extra=""/>
   <key Table="#__emundus_setup_campaigns" Non_unique="0" Key_name="PRIMARY" Seq_in_index="1" Column_name="id" Collation="A" Sub_part="" Null="" Index_type="BTREE" Comment=""/>
   <key Table="#__emundus_setup_campaigns" Non_unique="1" Key_name="user" Seq_in_index="1" Column_name="user" Collation="A" Sub_part="" Null="YES" Index_type="BTREE" Comment=""/>
   <key Table="#__emundus_setup_campaigns" Non_unique="1" Key_name="profile_id" Seq_in_index="1" Column_name="profile_id" Collation="A" Sub_part="" Null="YES" Index_type="BTREE" Comment=""/>
   <key Table="#__emundus_setup_campaigns" Non_unique="1" Key_name="year" Seq_in_index="1" Column_name="year" Collation="A" Sub_part="" Null="YES" Index_type="BTREE" Comment=""/>
   <key Table="#__emundus_setup_campaigns" Non_unique="1" Key_name="fb_filter_training_INDEX" Seq_in_index="1" Column_name="training" Collation="A" Sub_part="" Null="YES" Index_type="BTREE" Comment=""/>
   <key Table="#__emundus_setup_campaigns" Non_unique="1" Key_name="fb_filter_start_date_INDEX" Seq_in_index="1" Column_name="start_date" Collation="A" Sub_part="" Null="YES" Index_type="BTREE" Comment=""/>
   <key Table="#__emundus_setup_campaigns" Non_unique="1" Key_name="fb_filter_end_date_INDEX" Seq_in_index="1" Column_name="end_date" Collation="A" Sub_part="" Null="YES" Index_type="BTREE" Comment=""/>
   <key Table="#__emundus_setup_campaigns" Non_unique="1" Key_name="fb_filter_published_INDEX" Seq_in_index="1" Column_name="published" Collation="A" Sub_part="10" Null="YES" Index_type="BTREE" Comment=""/>
   <key Table="#__emundus_setup_campaigns" Non_unique="1" Key_name="fb_order_label_INDEX" Seq_in_index="1" Column_name="label" Collation="A" Sub_part="10" Null="YES" Index_type="BTREE" Comment=""/>
  </table_structure>
    <table_structure name="#__emundus_setup_scholarship">
   <field Field="id" Type="int(11)" Null="NO" Key="PRI" Extra="auto_increment"/>
   <field Field="value" Type="varchar(254)" Null="NO" Key="" Extra=""/>
   <field Field="description" Type="text" Null="NO" Key="" Extra=""/>
   <field Field="profile_id" Type="int(11)" Null="NO" Key="" Extra=""/>
   <field Field="ordering" Type="int(11)" Null="NO" Key="" Extra=""/>
   <key Table="#__emundus_setup_scholarship" Non_unique="0" Key_name="PRIMARY" Seq_in_index="1" Column_name="id" Collation="A" Sub_part="" Null="" Index_type="BTREE" Comment=""/>
  </table_structure>
  </database>
  <viewlevels>
    <viewlevel id="1" title="Public" ordering="0" rules="[1]"/>
    <viewlevel id="2" title="Registered" ordering="1" rules="[2]"/>
    <viewlevel id="3" title="Special" ordering="2" rules="[6,7,3,4,8]"/>
    <viewlevel id="4" title="Applicant" ordering="0" rules="[11]"/>
    <viewlevel id="5" title="Evaluator" ordering="0" rules="[6,7,3,4]"/>
    <viewlevel id="6" title="Partner" ordering="0" rules="[7,4,8]"/>
    <viewlevel id="7" title="Coordinator" ordering="0" rules="[7,4,8]"/>
    <viewlevel id="8" title="Administrator" ordering="0" rules="[8]"/>
    <viewlevel id="9" title="Guest" ordering="0" rules="[9]"/>
    <viewlevel id="10" title="Nobody" ordering="0" rules="[10]"/>
    <viewlevel id="11" title="form" ordering="0" rules="[7,3,2,11]"/>
  </viewlevels>
  <groups>
    <group id="1" parent_id="0" lft="1" rgt="22" title="Public"/>
    <group id="2" parent_id="1" lft="16" rgt="19" title="Registered"/>
    <group id="3" parent_id="6" lft="7" rgt="12" title="Author"/>
    <group id="4" parent_id="3" lft="8" rgt="11" title="Editor"/>
    <group id="5" parent_id="4" lft="9" rgt="10" title="Publisher"/>
    <group id="6" parent_id="1" lft="4" rgt="13" title="Manager"/>
    <group id="7" parent_id="6" lft="5" rgt="6" title="Administrator"/>
    <group id="8" parent_id="1" lft="20" rgt="21" title="Super Users"/>
    <group id="9" parent_id="1" lft="2" rgt="3" title="Guest"/>
    <group id="10" parent_id="1" lft="14" rgt="15" title="Nobody"/>
    <group id="11" parent_id="2" lft="17" rgt="18" title="Applicant"/>
  </groups>
</contenttype>
