<?xml version="1.0" encoding="utf-8"?>
<extension version="2.5" type="plugin" group="system" method="upgrade">
	<name>PLG_SYS_DSCONSTANT</name>
	<author>Roberto Segura - Digital Disseny</author>
	<creationDate>September 2012</creationDate>
	<copyright>Copyright (C) 2012 Digital Disseny, S.L. All rights reserved.</copyright>
	<license>http://www.gnu.org/licenses/gpl-2.0.html GNU/GPL</license>
	<authorEmail>roberto@digitaldisseny.com</authorEmail>
	<authorUrl>www.digitaldisseny.com</authorUrl>
	<version>1.0.1</version>
	<description>PLG_SYS_DSCONSTANT_XML_DESC</description>
	<files>
		<folder>language</folder>
		<filename plugin="dsconstant">dsconstant.php</filename>
		<filename>index.html</filename>
	</files>
	<languages>
		<!-- en-GB -->
		<language tag="en-GB">language/en-GB/en-GB.plg_system_dsconstant.ini</language>
		<language tag="en-GB">language/en-GB/en-GB.plg_system_dsconstant.sys.ini</language>
	</languages>
	<config>
	<fields name="params">
		<fieldset name="basic">
			<field name="frontend" type="radio"
				default="1"
				description="PLG_SYS_DSCONSTANT_FIELD_FRONTEND_DESC"
				label="PLG_SYS_DSCONSTANT_FIELD_FRONTEND_LABEL">
					<option value="1">JYes</option>
					<option value="0">JNo</option>
			</field>
			<field name="backend" type="radio"
				default="1"
				description="PLG_SYS_DSCONSTANT_FIELD_BACKEND_DESC"
				label="PLG_SYS_DSCONSTANT_FIELD_BACKEND_LABEL">
					<option value="1">JYes</option>
					<option value="0">JNo</option>
			</field>
		</fieldset>
		<fieldset name="advanced">
		</fieldset>
	</fields>
	</config>
</extension>